mysql_latin1_codec
