Metadata-Version: 1.1
Name: mysql-latin1-codec
Version: 2.0
Summary: Python string codec for MySQL's latin1 encoding
Home-page: https://github.com/wbolster/mysql-latin1-codec
Author: Wouter Bolsterlee
Author-email: uws@xs4all.nl
License: BSD License
Platform: UNKNOWN
Classifier: Development Status :: 5 - Production/Stable
Classifier: Intended Audience :: Developers
Classifier: License :: OSI Approved :: BSD License
Classifier: Programming Language :: Python
Classifier: Topic :: System :: Recovery Tools
Classifier: Topic :: Text Processing
